popolo/__init__.py
popolo/admin.py
popolo/apps.py
popolo/exceptions.py
popolo/managers.py
popolo/mixins.py
popolo/models.py
popolo/querysets.py
popolo/signals.py
popolo/urls.py
popolo/utils.py
popolo/validators.py
popolo/views.py
popolo/templates/area_detail.html
popolo/templates/electoral_event_detail.html
popolo/templates/membership_detail.html
popolo/templates/organization_detail.html
popolo/templates/person_detail.html
popolo/templates/post_detail.html
django_popolo-3.0.10.dist-info/AUTHORS
django_popolo-3.0.10.dist-info/LICENSE
django_popolo-3.0.10.dist-info/METADATA
django_popolo-3.0.10.dist-info/WHEEL
django_popolo-3.0.10.dist-info/top_level.txt
django_popolo-3.0.10.dist-info/RECORD
