Metadata-Version: 2.1
Name: django-popolo
Version: 3.0.10
Summary: A Django-based implementation of the OpenGovernment context, compliant with the Popolo data specifications.
Home-page: http://github.com/openpolis/django-popolo
Author: Guglielmo Celata
Author-email: guglielmo@openpolis.it
License: AGPL-3.0
Platform: UNKNOWN
Classifier: Topic :: Internet :: WWW/HTTP :: Dynamic Content
Classifier: Intended Audience :: Developers
Classifier: Programming Language :: Python
Classifier: Programming Language :: Python :: 3 :: Only
Classifier: Programming Language :: Python :: 3.5
Classifier: Programming Language :: Python :: 3.6
Classifier: Programming Language :: Python :: 3.7
Classifier: Programming Language :: Python :: 3.8
Classifier: Programming Language :: Python :: 3.9
Classifier: Framework :: Django
Classifier: Framework :: Django :: 1.11
Classifier: Framework :: Django :: 2.2
Classifier: Framework :: Django :: 3.2
Classifier: License :: OSI Approved :: GNU Affero General Public License v3
Classifier: Development Status :: 4 - Beta
Classifier: Operating System :: OS Independent
License-File: LICENSE
License-File: AUTHORS
Requires-Dist: django<3.3
Requires-Dist: django-autoslug<2
Requires-Dist: django-model-utils<5
Provides-Extra: dev
Requires-Dist: black; extra == "dev"
Requires-Dist: coverage; extra == "dev"
Provides-Extra: test
Requires-Dist: faker; extra == "test"
Requires-Dist: factory-boy; extra == "test"
